skelpy/__init__.py
skelpy/main.py
skelpy/makers/__init__.py
skelpy/makers/base.py
skelpy/makers/docs.py
skelpy/makers/license.py
skelpy/makers/license_change.py
skelpy/makers/package.py
skelpy/makers/project.py
skelpy/makers/readme.py
skelpy/makers/setup.py
skelpy/makers/setup_cfg.py
skelpy/makers/tests.py
skelpy/templates/.editorconfig.tpl
skelpy/templates/.gitignore.tpl
skelpy/templates/Makefile.tpl
skelpy/templates/__init__.py
skelpy/templates/info.tpl
skelpy/templates/license_apache.tpl
skelpy/templates/license_cc0_1.0.tpl
skelpy/templates/license_gpl_2.0.tpl
skelpy/templates/license_gpl_3.0.tpl
skelpy/templates/license_lgpl_2.1.tpl
skelpy/templates/license_lgpl_3.0.tpl
skelpy/templates/license_mit.tpl
skelpy/templates/license_mozilla.tpl
skelpy/templates/license_new_bsd.tpl
skelpy/templates/license_proprietary.tpl
skelpy/templates/license_simplified_bsd.tpl
skelpy/templates/main.tpl
skelpy/templates/make_bat.tpl
skelpy/templates/readme.tpl
skelpy/templates/setup.tpl
skelpy/templates/setup_cfg.tpl
skelpy/templates/sphinx_conf.tpl
skelpy/templates/sphinx_index.tpl
skelpy/templates/test_init.tpl
skelpy/templates/test_main_pytest.tpl
skelpy/templates/test_main_unittest.tpl
skelpy/utils/__init__.py
skelpy/utils/defaultsubparse.py
skelpy/utils/helpers.py
skelpy/utils/logger.py
skelpy/utils/opener.py
skelpy-1.0.0.dist-info/LICENSE
skelpy-1.0.0.dist-info/METADATA
skelpy-1.0.0.dist-info/WHEEL
skelpy-1.0.0.dist-info/entry_points.txt
skelpy-1.0.0.dist-info/top_level.txt
skelpy-1.0.0.dist-info/zip-safe
skelpy-1.0.0.dist-info/RECORD
