Metadata-Version: 2.1
Name: skelpy
Version: 1.0.0
Summary: A simple template tool to create the skeleton for a python project
Home-page: https://github.com/june3474/skelpy
Author: dks
Author-email: june3474@gmail.com
License: MIT
Platform: any
Classifier: Environment :: Console
Classifier: Operating System :: OS Independent
Classifier: Programming Language :: Python :: 2.7
Classifier: Programming Language :: Python :: 3
Classifier: Topic :: Utilities
Requires-Python: >=2.7
